bodyguard/__init__.py
bodyguard/convert.py
bodyguard/dicts.py
bodyguard/dimension_reduction.py
bodyguard/distance.py
bodyguard/exceptions.py
bodyguard/init.py
bodyguard/lists.py
bodyguard/pca.py
bodyguard/predict.py
bodyguard/read_and_write.py
bodyguard/sanity_check.py
bodyguard/strings.py
bodyguard/tools.py
bodyguard-0.0.77.dist-info/LICENSE
bodyguard-0.0.77.dist-info/METADATA
bodyguard-0.0.77.dist-info/WHEEL
bodyguard-0.0.77.dist-info/top_level.txt
bodyguard-0.0.77.dist-info/RECORD
