Metadata-Version: 2.1
Name: bodyguard
Version: 0.0.77
Summary: Heavy machinery for Python (tools, utilities, etc)
Home-page: https://github.com/muhlbach/bodyguard
Author: Nicolaj Søndergaard Mühlbach
Author-email: n.muhlbach@gmail.com
License: MIT License
Keywords: utilities,tools
Classifier: Programming Language :: Python :: 3
Classifier: License :: OSI Approved :: MIT License
Classifier: Operating System :: OS Independent
Requires-Python: >=3.6
License-File: LICENSE
Requires-Dist: pandas (>=1.5)
Requires-Dist: numpy (>=1.21)
Requires-Dist: scipy (>=1.9)
Requires-Dist: scikit-learn (>=1.0)
Provides-Extra: plot
Requires-Dist: plotnine ; extra == 'plot'
